{
  "generated_at": "2026-01-05T15:15:28.253416+08:00",
  "total_titles_processed": 1274,
  "failed_sources": [],
  "trends": [
    {
      "keyword_group": "特朗普",
      "match_count": 83,
      "titles": [
        {
          "title": "上周六新建账号、本周五下注“马杜罗被抓”、周日爆赚1242%--Polymarket又见“特朗普内幕交易”？",
          "url": "https://wallstreetcn.com/articles/3762495",
          "source": "华尔街见闻",
          "ranks": [
            3,
            2
          ],
          "is_new": false,
          "appearance_count": 18,
          "time_info": "[00时08分 ~ 10时55分]"
        },
        {
          "title": "开发委内瑞拉“全球第一的原油储备”？特朗普“理想很丰满”，但“现实很骨感”",
          "url": "https://wallstreetcn.com/articles/3762494",
          "source": "华尔街见闻",
          "ranks": [
            6,
            5
          ],
          "is_new": false,
          "appearance_count": 18,
          "time_info": "[00时08分 ~ 10时55分]"
        },
        {
          "title": "美国“闪击”委内瑞拉：特朗普称将“管理”委内瑞拉直至实施“安全”过渡，深度介入石油产业",
          "url": "https://wallstreetcn.com/articles/3762484",
          "source": "华尔街见闻",
          "ranks": [
            1
          ],
          "is_new": false,
          "appearance_count": 6,
          "time_info": "[00时08分 ~ 02时11分]"
        },
        {
          "title": "特朗普威胁委内瑞拉代总统：若不正确行事 将付出更惨痛代价",
          "url": "https://www.cls.cn/detail/2247373",
          "source": "财联社热门",
          "ranks": [
            9,
            8,
            7,
            6,
            4,
            5
          ],
          "is_new": false,
          "appearance_count": 9,
          "time_info": "[09时38分 ~ 15时15分]"
        },
        {
          "title": "特朗普为美企进军委内瑞拉“吹号”：准备好“为美国赚钱”",
          "url": "https://news.ifeng.com/c/8peBKHvPx8Z",
          "source": "凤凰网",
          "ranks": [
            7
          ],
          "is_new": false,
          "appearance_count": 13,
          "time_info": "[00时08分 ~ 07时08分]"
        },
        {
          "title": "特朗普威胁委代理总统，还称“绝对需要格陵兰岛”",
          "url": "https://m.thepaper.cn/newsDetail_forward_32315820",
          "source": "澎湃新闻",
          "ranks": [
            11,
            10,
            9,
            8
          ],
          "is_new": false,
          "appearance_count": 11,
          "time_info": "[08时36分 ~ 15时15分]"
        },
        {
          "title": "特朗普威胁古巴哥伦比亚",
          "url": "https://www.douyin.com/hot/2356597",
          "source": "抖音",
          "ranks": [
            11,
            13,
            12
          ],
          "is_new": false,
          "appearance_count": 13,
          "time_info": "[00时08分 ~ 07时08分]"
        },
        {
          "title": "特朗普威胁委代总统或付“沉重代价”",
          "url": "https://www.toutiao.com/trending/7591475606379154985/",
          "source": "今日头条",
          "ranks": [
            11,
            14,
            19,
            17
          ],
          "is_new": false,
          "appearance_count": 10,
          "time_info": "[08时36分 ~ 14时15分]"
        },
        {
          "title": "特朗普在抓捕马杜罗发布会上称已超越门罗主义，升级为唐罗主义，这反映了怎样的政策转向？核心主张是什么？",
          "url": "https://www.zhihu.com/question/1991082437355201732",
          "source": "知乎",
          "ranks": [
            18,
            17,
            16
          ],
          "is_new": false,
          "appearance_count": 20,
          "time_info": "[00时08分 ~ 11时43分]"
        },
        {
          "title": "特朗普称美国将管理委内瑞拉",
          "url": "https://search.bilibili.com/all?keyword=%E7%BE%8E%E5%9B%BD%E5%B0%86%E7%AE%A1%E7%90%86%E5%A7%94%E5%86%85%E7%91%9E%E6%8B%89",
          "source": "bilibili 热搜",
          "ranks": [
            28,
            30,
            21,
            25
          ],
          "is_new": false,
          "appearance_count": 9,
          "time_info": "[00时08分 ~ 12时32分]"
        },
        {
          "title": "委内瑞拉全面战备，国际社会持续反对，特朗普：还没完",
          "url": "https://news.ifeng.com/c/8peoBGO9yZ7",
          "source": "凤凰网",
          "ranks": [
            3
          ],
          "is_new": false,
          "appearance_count": 4,
          "time_info": "[08时36分 ~ 09时39分]"
        },
        {
          "title": "美国国务卿卢比奥：石油对委内瑞拉的未来具有至关重要的意义。 （特朗普政府）在委内瑞拉（军事行动的）目标包括不再发生毒品输送，并切断与伊朗的联系。 （对于总统马杜罗）政府官员，我们已经虏获最高目标。 不在委内瑞拉陆地展开数日行动，是无法掳走更多人员的。 委内瑞拉并不存在美国的地面部队。 （对于占领委内瑞拉）总统特朗普保留这样的选项。 委内瑞拉实现民主过渡需要时间，不可能在几个小时内发生。 我将深度介入委内瑞拉的政权过渡。 将判断副总统Rodriguez的行动。 预计委内瑞拉将发生变化。 石油禁运是美国在委内瑞拉一个主要的杠杆。 需要再投资委内瑞拉石油，需要私人公司参与。 委内瑞拉的大多数机会在其国家之外。",
          "url": "https://wallstreetcn.com/livenews/3030342",
          "source": "华尔街见闻-快讯",
          "ranks": [
            6,
            20
          ],
          "is_new": false,
          "appearance_count": 8,
          "time_info": "[00时09分 ~ 07时08分]"
        },
        {
          "title": "特朗普威胁委内瑞拉代总统：若不配合美国 将付出更惨痛代价",
          "url": "https://www.cls.cn/detail/2247429",
          "source": "财联社热门",
          "ranks": [
            13,
            9,
            8,
            5,
            6
          ],
          "is_new": false,
          "appearance_count": 7,
          "time_info": "[10时55分 ~ 15时15分]"
        },
        {
          "title": "好莱坞明星入籍法国，特朗普发帖讽刺，本人回击",
          "url": "https://news.ifeng.com/c/8peoOMfJqxB",
          "source": "凤凰网",
          "ranks": [
            11
          ],
          "is_new": false,
          "appearance_count": 8,
          "time_info": "[09时38分 ~ 14时15分]"
        },
        {
          "title": "特朗普称“绝对需要格陵兰岛”",
          "url": "https://www.baidu.com/s?wd=%E7%89%B9%E6%9C%97%E6%99%AE%E7%A7%B0%E2%80%9C%E7%BB%9D%E5%AF%B9%E9%9C%80%E8%A6%81%E6%A0%BC%E9%99%B5%E5%85%B0%E5%B2%9B%E2%80%9D",
          "source": "百度热搜",
          "ranks": [
            28,
            24,
            12,
            14
          ],
          "is_new": false,
          "appearance_count": 8,
          "time_info": "[09时38分 ~ 14时15分]"
        },
        {
          "title": "美国是否会在哥伦比亚开展行动？特朗普：这听上去挺不错的",
          "url": "https://wallstreetcn.com/articles/3762529",
          "source": "华尔街见闻",
          "ranks": [
            8,
            7,
            5
          ],
          "is_new": false,
          "appearance_count": 6,
          "time_info": "[11时42分 ~ 15时15分]"
        },
        {
          "title": "如何看待特朗普每天服用过量阿司匹林",
          "url": "https://www.toutiao.com/trending/7591309116983742003/",
          "source": "今日头条",
          "ranks": [
            8,
            5
          ],
          "is_new": false,
          "appearance_count": 5,
          "time_info": "[05时07分 ~ 07时08分]"
        },
        {
          "title": "特朗普说绝对需要格陵兰岛",
          "url": "https://s.weibo.com/weibo?q=%23%E7%89%B9%E6%9C%97%E6%99%AE%E8%AF%B4%E7%BB%9D%E5%AF%B9%E9%9C%80%E8%A6%81%E6%A0%BC%E9%99%B5%E5%85%B0%E5%B2%9B%23&t=31&band_rank=8&Refer=top",
          "source": "微博",
          "ranks": [
            8,
            15,
            29
          ],
          "is_new": false,
          "appearance_count": 7,
          "time_info": "[08时36分 ~ 11时43分]"
        },
        {
          "title": "特朗普威胁委代总统：或付出更惨代价",
          "url": "https://www.baidu.com/s?wd=%E7%89%B9%E6%9C%97%E6%99%AE%E5%A8%81%E8%83%81%E5%A7%94%E4%BB%A3%E6%80%BB%E7%BB%9F%EF%BC%9A%E6%88%96%E4%BB%98%E5%87%BA%E6%9B%B4%E6%83%A8%E4%BB%A3%E4%BB%B7",
          "source": "百度热搜",
          "ranks": [
            12,
            21
          ],
          "is_new": false,
          "appearance_count": 7,
          "time_info": "[08时36分 ~ 11时43分]"
        },
        {
          "title": "以色列总理内塔尼亚胡谈及委内瑞拉局势，表示以色列政府支持美国“恢复自由与正义”的决定与行动，对特朗普的决定表示祝贺，并向执行行动的美军致意。（央视）",
          "url": "https://wallstreetcn.com/livenews/3030327",
          "source": "华尔街见闻-快讯",
          "ranks": [
            19
          ],
          "is_new": false,
          "appearance_count": 7,
          "time_info": "[00时09分 ~ 06时08分]"
        },
        {
          "title": "特朗普政府要求美国石油公司投资委内瑞拉，业内对此态度审慎",
          "url": "https://wallstreetcn.com/livenews/3030325",
          "source": "华尔街见闻-快讯",
          "ranks": [
            21
          ],
          "is_new": false,
          "appearance_count": 7,
          "time_info": "[00时09分 ~ 06时08分]"
        },
        {
          "title": "“如果她不做正确的事，可能比马杜罗更惨”！特朗普警告委内瑞拉“代总统”：必须听美国的",
          "url": "https://wallstreetcn.com/articles/3762521",
          "source": "华尔街见闻",
          "ranks": [
            10,
            8,
            7
          ],
          "is_new": false,
          "appearance_count": 6,
          "time_info": "[11时42分 ~ 15时15分]"
        },
        {
          "title": "丹麦首相弗雷德里克森：美国总统特朗普必须停止其关于格陵兰岛的威胁。",
          "url": "https://flash.jin10.com/detail/20260105034320871800",
          "source": "金十数据",
          "ranks": [
            1
          ],
          "is_new": false,
          "appearance_count": 1,
          "time_info": "04时09分"
        },
        {
          "title": "特朗普：委内瑞拉是一个“死掉的国家”，美国“正在掌权”",
          "url": "https://news.ifeng.com/c/8pf4IXU084i",
          "source": "凤凰网",
          "ranks": [
            2
          ],
          "is_new": true,
          "appearance_count": 1,
          "time_info": "15时15分"
        },
        {
          "title": "美国总统特朗普：美国对委内瑞拉的行动关乎世界和平。",
          "url": "https://flash.jin10.com/detail/20260105091902527800",
          "source": "金十数据",
          "ranks": [
            3
          ],
          "is_new": false,
          "appearance_count": 1,
          "time_info": "09时39分"
        },
        {
          "title": "日本首相高市早苗：将与美国保持各层级密切沟通；已收到特朗普的访美邀请。",
          "url": "https://flash.jin10.com/detail/20260105140242641800",
          "source": "金十数据",
          "ranks": [
            3
          ],
          "is_new": false,
          "appearance_count": 1,
          "time_info": "14时15分"
        },
        {
          "title": "美国总统特朗普：我们要夺回委内瑞拉偷走的东西。",
          "url": "https://flash.jin10.com/detail/20260105091745044800",
          "source": "金十数据",
          "ranks": [
            4
          ],
          "is_new": false,
          "appearance_count": 1,
          "time_info": "09时39分"
        },
        {
          "title": "美国总统特朗普：埃隆·马斯克很棒；马斯克80%是天才，20%是犯错。",
          "url": "https://flash.jin10.com/detail/20260105091648820800",
          "source": "金十数据",
          "ranks": [
            5
          ],
          "is_new": false,
          "appearance_count": 1,
          "time_info": "09时39分"
        },
        {
          "title": "美国国务卿鲁比奥：特朗普在委内瑞拉行动上始终拥有多种选择",
          "url": "https://flash.jin10.com/detail/20260105042758533800",
          "source": "金十数据",
          "ranks": [
            2,
            11,
            21
          ],
          "is_new": false,
          "appearance_count": 3,
          "time_info": "[05时07分 ~ 07时08分]"
        },
        {
          "title": "马斯克表示，昨晚其与美国总统特朗普及美国第一夫人共进了晚餐。",
          "url": "https://flash.jin10.com/detail/20260105042649832800",
          "source": "金十数据",
          "ranks": [
            3,
            12,
            22
          ],
          "is_new": false,
          "appearance_count": 3,
          "time_info": "[05时07分 ~ 07时08分]"
        },
        {
          "title": "美国总统特朗普在《大西洋》月刊采访中表示，委内瑞拉副总统德尔茜·罗德里格斯“若不行正道”将付出比马杜罗更惨痛代价。",
          "url": "https://flash.jin10.com/detail/20260105012834419800",
          "source": "金十数据",
          "ranks": [
            2,
            10
          ],
          "is_new": false,
          "appearance_count": 2,
          "time_info": "[02时11分 ~ 03时07分]"
        },
        {
          "title": "特朗普威胁委内瑞拉代总统",
          "url": "https://flash.jin10.com/detail/20260105021301482800",
          "source": "金十数据",
          "ranks": [
            2,
            23
          ],
          "is_new": false,
          "appearance_count": 2,
          "time_info": "[03时07分 ~ 04时09分]"
        },
        {
          "title": "俄罗斯联邦安全委员会副主席梅德韦杰夫：特朗普在委内瑞拉的行为虽属非法，但符合其一贯捍卫美国利益的作风。",
          "url": "https://flash.jin10.com/detail/20260104225319283800",
          "source": "金十数据",
          "ranks": [
            7,
            13,
            20,
            28
          ],
          "is_new": false,
          "appearance_count": 4,
          "time_info": "[00时09分 ~ 03时07分]"
        },
        {
          "title": "委内瑞拉后恐是格陵兰岛，丹麦首相强硬回应特朗普！",
          "url": "https://www.cls.cn/detail/2247392",
          "source": "财联社热门",
          "ranks": [
            11,
            10
          ],
          "is_new": false,
          "appearance_count": 4,
          "time_info": "[12时32分 ~ 15时15分]"
        },
        {
          "title": "特朗普宣布美国接管委内瑞拉，将让美石油巨头进入委内瑞拉，意味着什么？委内瑞拉接下来将面临哪些危机？",
          "url": "https://www.zhihu.com/question/1991053595043390487",
          "source": "知乎",
          "ranks": [
            17,
            19
          ],
          "is_new": false,
          "appearance_count": 4,
          "time_info": "[11时42分 ~ 15时15分]"
        },
        {
          "title": "高志凯：特朗普诺奖妄想被彻底打碎",
          "url": "https://www.toutiao.com/trending/7590552658361614387/",
          "source": "今日头条",
          "ranks": [
            22,
            28
          ],
          "is_new": false,
          "appearance_count": 4,
          "time_info": "[08时36分 ~ 09时39分]"
        },
        {
          "title": "丹麦首相敦促特朗普停止威胁接管格陵兰岛",
          "url": "https://flash.jin10.com/detail/20260105035320054800",
          "source": "金十数据",
          "ranks": [
            6,
            15,
            25
          ],
          "is_new": false,
          "appearance_count": 3,
          "time_info": "[05时07分 ~ 07时08分]"
        },
        {
          "title": "丹麦首相弗雷泽里克森：美国总统特朗普必须停止其关于格陵兰岛的威胁。",
          "url": "https://flash.jin10.com/detail/20260105034320871800",
          "source": "金十数据",
          "ranks": [
            9,
            18,
            28
          ],
          "is_new": false,
          "appearance_count": 3,
          "time_info": "[05时07分 ~ 07时08分]"
        },
        {
          "title": "特朗普称美国“掌控着委内瑞拉”",
          "url": "https://www.toutiao.com/trending/7591367635717373988/",
          "source": "今日头条",
          "ranks": [
            11,
            16,
            14
          ],
          "is_new": false,
          "appearance_count": 3,
          "time_info": "[12时32分 ~ 14时15分]"
        },
        {
          "title": "特朗普称美方正与委代总统接触",
          "url": "https://www.toutiao.com/trending/7591367635717373988/",
          "source": "今日头条",
          "ranks": [
            20,
            14
          ],
          "is_new": false,
          "appearance_count": 3,
          "time_info": "[10时55分 ~ 11时43分]"
        },
        {
          "title": "特朗普称美需全面获取委石油及资源",
          "url": "https://www.toutiao.com/trending/7591716415548313126/",
          "source": "今日头条",
          "ranks": [
            25,
            29,
            28
          ],
          "is_new": false,
          "appearance_count": 3,
          "time_info": "[13时19分 ~ 15时15分]"
        },
        {
          "title": "丹麦首相：美国总统特朗普必须停止其关于格陵兰岛的威胁。谈论美国需要接管格陵兰岛毫无道理；美国无权“吞并”丹麦王国中的任何一处。",
          "url": "https://flash.jin10.com/detail/20260105045144855800",
          "source": "金十数据",
          "ranks": [
            7,
            17
          ],
          "is_new": false,
          "appearance_count": 2,
          "time_info": "[06时08分 ~ 07时08分]"
        },
        {
          "title": "市场消息：美国总统特朗普将于美国东部时间周一下午3:30（北京时间次日凌晨4:30）参加政策会议。",
          "url": "https://flash.jin10.com/detail/20260105120651900800",
          "source": "金十数据",
          "ranks": [
            8,
            21
          ],
          "is_new": false,
          "appearance_count": 2,
          "time_info": "[12时32分 ~ 13时19分]"
        },
        {
          "title": "“特马”重修旧好？美国突袭委内瑞拉后 特朗普和马斯克共进晚餐",
          "url": "https://www.cls.cn/detail/2247636",
          "source": "财联社热门",
          "ranks": [
            13,
            10
          ],
          "is_new": false,
          "appearance_count": 2,
          "time_info": "[14时15分 ~ 15时15分]"
        },
        {
          "title": "美军委内瑞拉行动引发党争 民主党人呼吁弹劾特朗普",
          "url": "https://www.cls.cn/detail/2247292",
          "source": "财联社热门",
          "ranks": [
            12
          ],
          "is_new": false,
          "appearance_count": 2,
          "time_info": "[12时32分 ~ 14时15分]"
        },
        {
          "title": "特朗普暗示可能对墨西哥采取行动",
          "url": "https://s.weibo.com/weibo?q=%23%E7%89%B9%E6%9C%97%E6%99%AE%E6%9A%97%E7%A4%BA%E5%8F%AF%E8%83%BD%E5%AF%B9%E5%A2%A8%E8%A5%BF%E5%93%A5%E9%87%87%E5%8F%96%E8%A1%8C%E5%8A%A8%23&t=31&band_rank=19&Refer=top",
          "source": "微博",
          "ranks": [
            19,
            25
          ],
          "is_new": false,
          "appearance_count": 2,
          "time_info": "[13时19分 ~ 14时15分]"
        },
        {
          "title": "特朗普政府要求美国石油公司投资委内瑞拉",
          "url": "https://flash.jin10.com/detail/20260104204048321800",
          "source": "金十数据",
          "ranks": [
            19,
            25
          ],
          "is_new": false,
          "appearance_count": 2,
          "time_info": "[00时09分 ~ 01时08分]"
        },
        {
          "title": "特朗普改口称不相信乌袭击普京官邸",
          "url": "https://www.baidu.com/s?wd=%E7%89%B9%E6%9C%97%E6%99%AE%E6%94%B9%E5%8F%A3%E7%A7%B0%E4%B8%8D%E7%9B%B8%E4%BF%A1%E4%B9%8C%E8%A2%AD%E5%87%BB%E6%99%AE%E4%BA%AC%E5%AE%98%E9%82%B8",
          "source": "百度热搜",
          "ranks": [
            24,
            20
          ],
          "is_new": false,
          "appearance_count": 2,
          "time_info": "[14时15分 ~ 15时15分]"
        },
        {
          "title": "特朗普与马斯克罕见同框现身宴会",
          "url": "https://www.toutiao.com/trending/7591135835124842559/",
          "source": "今日头条",
          "ranks": [
            28
          ],
          "is_new": false,
          "appearance_count": 2,
          "time_info": "[08时36分 ~ 08时37分]"
        },
        {
          "title": "特朗普：美方正与委代总统接触",
          "url": "https://www.baidu.com/s?wd=%E7%89%B9%E6%9C%97%E6%99%AE%EF%BC%9A%E7%BE%8E%E6%96%B9%E6%AD%A3%E4%B8%8E%E5%A7%94%E4%BB%A3%E6%80%BB%E7%BB%9F%E6%8E%A5%E8%A7%A6",
          "source": "百度热搜",
          "ranks": [
            30
          ],
          "is_new": false,
          "appearance_count": 2,
          "time_info": "[12时32分 ~ 13时19分]"
        },
        {
          "title": "美国总统特朗普：我认为不需要美国对古巴采取任何军事行动，古巴会自行沦陷。",
          "url": "https://flash.jin10.com/detail/20260105091621842800",
          "source": "金十数据",
          "ranks": [
            6
          ],
          "is_new": false,
          "appearance_count": 1,
          "time_info": "09时39分"
        },
        {
          "title": "美国总统特朗普：马杜罗杀害了数百万人。",
          "url": "https://flash.jin10.com/detail/20260105091448056800",
          "source": "金十数据",
          "ranks": [
            8
          ],
          "is_new": false,
          "appearance_count": 1,
          "time_info": "09时39分"
        },
        {
          "title": "美国总统特朗普：不相信所谓的乌克兰袭击俄罗斯总统普京住所的事件真的发生过。",
          "url": "https://flash.jin10.com/detail/20260105091352495800",
          "source": "金十数据",
          "ranks": [
            9
          ],
          "is_new": false,
          "appearance_count": 1,
          "time_info": "09时39分"
        },
        {
          "title": "美国总统特朗普：与马杜罗还没有所谓的“终局”，我们将走完整个审判程序。",
          "url": "https://flash.jin10.com/detail/20260105091341117800",
          "source": "金十数据",
          "ranks": [
            10
          ],
          "is_new": false,
          "appearance_count": 1,
          "time_info": "09时39分"
        },
        {
          "title": "特朗普威胁委代理总统 还称“绝对需要格陵兰岛”",
          "url": "https://wallstreetcn.com/livenews/3030354",
          "source": "华尔街见闻-快讯",
          "ranks": [
            10
          ],
          "is_new": false,
          "appearance_count": 1,
          "time_info": "07时08分"
        },
        {
          "title": "美国总统特朗普：如果事态发展不顺利，委内瑞拉代理总统罗德里格斯面临的处境可能比马杜罗更糟。",
          "url": "https://flash.jin10.com/detail/20260105091134980800",
          "source": "金十数据",
          "ranks": [
            11
          ],
          "is_new": false,
          "appearance_count": 1,
          "time_info": "09时39分"
        },
        {
          "title": "特朗普对西半球多国发出警告 称不再容忍毒品流入美国",
          "url": "https://flash.jin10.com/detail/20260105102045740800",
          "source": "金十数据",
          "ranks": [
            11
          ],
          "is_new": false,
          "appearance_count": 1,
          "time_info": "10时55分"
        },
        {
          "title": "美国总统特朗普：马杜罗举起双手投降了。",
          "url": "https://flash.jin10.com/detail/20260105091017399800",
          "source": "金十数据",
          "ranks": [
            12
          ],
          "is_new": false,
          "appearance_count": 1,
          "time_info": "09时39分"
        },
        {
          "title": "美国总统特朗普：古巴看起来似乎随时会垮台。",
          "url": "https://flash.jin10.com/detail/20260105091002679800",
          "source": "金十数据",
          "ranks": [
            14
          ],
          "is_new": false,
          "appearance_count": 1,
          "time_info": "09时39分"
        },
        {
          "title": "美国总统特朗普：欧盟需要我们拥有格陵兰岛。",
          "url": "https://flash.jin10.com/detail/20260105090749697800",
          "source": "金十数据",
          "ranks": [
            16
          ],
          "is_new": false,
          "appearance_count": 1,
          "time_info": "09时39分"
        },
        {
          "title": "特朗普：为了国家安全，我们需要格陵兰岛。欧洲知道我们需要格陵兰岛。",
          "url": "https://wallstreetcn.com/livenews/3030433",
          "source": "华尔街见闻-快讯",
          "ranks": [
            16
          ],
          "is_new": false,
          "appearance_count": 1,
          "time_info": "09时39分"
        },
        {
          "title": "美国总统特朗普：我们需要格陵兰岛。",
          "url": "https://flash.jin10.com/detail/20260105090710331800",
          "source": "金十数据",
          "ranks": [
            17
          ],
          "is_new": false,
          "appearance_count": 1,
          "time_info": "09时39分"
        },
        {
          "title": "美媒：马杜罗的舞蹈是特朗普发动袭击的诱因之一",
          "url": "https://wallstreetcn.com/livenews/3030389",
          "source": "华尔街见闻-快讯",
          "ranks": [
            17
          ],
          "is_new": false,
          "appearance_count": 1,
          "time_info": "08时37分"
        },
        {
          "title": "美国总统特朗普：我不想谈格陵兰岛，我们会在20天到2个月后再考虑格陵兰岛的问题。",
          "url": "https://flash.jin10.com/detail/20260105090701874800",
          "source": "金十数据",
          "ranks": [
            18
          ],
          "is_new": false,
          "appearance_count": 1,
          "time_info": "09时39分"
        },
        {
          "title": "特朗普：美国需要获得委内瑞拉石油及其他资源的全面准入权。",
          "url": "https://wallstreetcn.com/livenews/3030430",
          "source": "华尔街见闻-快讯",
          "ranks": [
            18
          ],
          "is_new": false,
          "appearance_count": 1,
          "time_info": "09时39分"
        },
        {
          "title": "特朗普称美国已“掌控”委内瑞拉",
          "url": "https://www.toutiao.com/trending/7591367635717373988/",
          "source": "今日头条",
          "ranks": [
            19
          ],
          "is_new": true,
          "appearance_count": 1,
          "time_info": "15时15分"
        },
        {
          "title": "特朗普：委内瑞拉是一个“死掉的国家”，而美国“正在掌权”",
          "url": "https://wallstreetcn.com/livenews/3030462",
          "source": "华尔街见闻-快讯",
          "ranks": [
            19
          ],
          "is_new": false,
          "appearance_count": 1,
          "time_info": "10时55分"
        },
        {
          "title": "美国总统特朗普：如果我们重返战场，我们将动用国民警卫队。我正在考虑在任何地方启用叛乱法。",
          "url": "https://flash.jin10.com/detail/20260105090625859800",
          "source": "金十数据",
          "ranks": [
            20
          ],
          "is_new": false,
          "appearance_count": 1,
          "time_info": "09时39分"
        },
        {
          "title": "特朗普称正在考虑重新开放美国驻委内瑞拉大使馆",
          "url": "https://wallstreetcn.com/livenews/3030460",
          "source": "华尔街见闻-快讯",
          "ranks": [
            20
          ],
          "is_new": false,
          "appearance_count": 1,
          "time_info": "10时55分"
        },
        {
          "title": "美国总统特朗普：美国需要完全获取委内瑞拉的石油和其他资源。",
          "url": "https://flash.jin10.com/detail/20260105090601427800",
          "source": "金十数据",
          "ranks": [
            21
          ],
          "is_new": false,
          "appearance_count": 1,
          "time_info": "09时39分"
        },
        {
          "title": "美国总统特朗普：如果印度不在俄罗斯石油问题上提供帮助，我们可能会提高对印度的关税。",
          "url": "https://wallstreetcn.com/livenews/3030426",
          "source": "华尔街见闻-快讯",
          "ranks": [
            21
          ],
          "is_new": false,
          "appearance_count": 1,
          "time_info": "09时39分"
        },
        {
          "title": "美国总统特朗普：我们已经撤退了，但我们会适时（带着国民警卫队）重新投入战斗。",
          "url": "https://flash.jin10.com/detail/20260105090525475800",
          "source": "金十数据",
          "ranks": [
            22
          ],
          "is_new": false,
          "appearance_count": 1,
          "time_info": "09时39分"
        },
        {
          "title": "美媒：马杜罗的舞蹈是特朗普发动袭击的诱因之一",
          "url": "https://flash.jin10.com/detail/20260105073333400800",
          "source": "金十数据",
          "ranks": [
            23
          ],
          "is_new": false,
          "appearance_count": 1,
          "time_info": "08时37分"
        },
        {
          "title": "美国总统特朗普：我们不会向明尼苏达州、加利福尼亚州或伊利诺伊州支付任何费用。",
          "url": "https://flash.jin10.com/detail/20260105090423156800",
          "source": "金十数据",
          "ranks": [
            23
          ],
          "is_new": false,
          "appearance_count": 1,
          "time_info": "09时39分"
        },
        {
          "title": "特朗普：认为在某个时点会就俄乌问题达成协议。",
          "url": "https://wallstreetcn.com/livenews/3030423",
          "source": "华尔街见闻-快讯",
          "ranks": [
            24
          ],
          "is_new": false,
          "appearance_count": 1,
          "time_info": "09时39分"
        },
        {
          "title": "哥伦比亚外交部强烈反对特朗普不当言论",
          "url": "https://wallstreetcn.com/livenews/3030614",
          "source": "华尔街见闻-快讯",
          "ranks": [
            24
          ],
          "is_new": true,
          "appearance_count": 1,
          "time_info": "15时15分"
        },
        {
          "title": "哥伦比亚总统佩特罗强硬喊话特朗普",
          "url": "https://wallstreetcn.com/livenews/3030613",
          "source": "华尔街见闻-快讯",
          "ranks": [
            25
          ],
          "is_new": true,
          "appearance_count": 1,
          "time_info": "15时15分"
        },
        {
          "title": "美国总统特朗普：根本不存在所谓的“稀土”这种东西，实际上到处都有稀土。",
          "url": "https://flash.jin10.com/detail/20260105090208177800",
          "source": "金十数据",
          "ranks": [
            26
          ],
          "is_new": false,
          "appearance_count": 1,
          "time_info": "09时39分"
        },
        {
          "title": "特朗普改口称不相信乌袭击普京官邸",
          "url": "https://www.toutiao.com/trending/7591134271677808681/",
          "source": "今日头条",
          "ranks": [
            27
          ],
          "is_new": true,
          "appearance_count": 1,
          "time_info": "15时15分"
        },
        {
          "title": "美国总统特朗普：如果印度在俄罗斯石油问题上不给予协助，我们可能会提高对印度的关税。",
          "url": "https://flash.jin10.com/detail/20260105090104872800",
          "source": "金十数据",
          "ranks": [
            27
          ],
          "is_new": false,
          "appearance_count": 1,
          "time_info": "09时39分"
        },
        {
          "title": "特朗普称针对马杜罗的案件“无懈可击”",
          "url": "https://flash.jin10.com/detail/20260105100351248800",
          "source": "金十数据",
          "ranks": [
            27
          ],
          "is_new": false,
          "appearance_count": 1,
          "time_info": "10时55分"
        },
        {
          "title": "美国总统特朗普：将考虑重开美国驻加拉加斯大使馆。",
          "url": "https://wallstreetcn.com/livenews/3030419",
          "source": "华尔街见闻-快讯",
          "ranks": [
            27
          ],
          "is_new": false,
          "appearance_count": 1,
          "time_info": "09时39分"
        },
        {
          "title": "美国总统特朗普：哥伦比亚“问题很大”。 哥伦比亚的领导人是个病态，他不会做很久。 哥伦比亚行动听起来不错。",
          "url": "https://wallstreetcn.com/livenews/3030417",
          "source": "华尔街见闻-快讯",
          "ranks": [
            29
          ],
          "is_new": false,
          "appearance_count": 1,
          "time_info": "09时39分"
        }
      ]
    },
    {
      "keyword_group": "美元",
      "match_count": 25,
      "titles": [
        {
          "title": "马杜罗被美国“闪击”，委内瑞拉“传说中的600亿美元比特币”会流向何方？",
          "url": "https://wallstreetcn.com/articles/3762490",
          "source": "华尔街见闻",
          "ranks": [
            4,
            3
          ],
          "is_new": false,
          "appearance_count": 17,
          "time_info": "[00时08分 ~ 09时39分]"
        },
        {
          "title": "现货钯金突破1700美元/盎司，日内涨4.18%。",
          "url": "https://flash.jin10.com/detail/20260105081300024800",
          "source": "金十数据",
          "ranks": [
            1
          ],
          "is_new": false,
          "appearance_count": 1,
          "time_info": "08时37分"
        },
        {
          "title": "现货白银涨3%报74.81美元/盎司。",
          "url": "https://wallstreetcn.com/livenews/3030405",
          "source": "华尔街见闻-快讯",
          "ranks": [
            4
          ],
          "is_new": false,
          "appearance_count": 1,
          "time_info": "08时37分"
        },
        {
          "title": "新加坡元兑美元跌至1.2888，为自去年12月22日以来的最低水平。",
          "url": "https://flash.jin10.com/detail/20260105111011322800",
          "source": "金十数据",
          "ranks": [
            5
          ],
          "is_new": false,
          "appearance_count": 1,
          "time_info": "11时43分"
        },
        {
          "title": "机构：委内瑞拉石油业复苏或需千亿美元成本且耗费数年时间",
          "url": "https://flash.jin10.com/detail/20260105103958701800",
          "source": "金十数据",
          "ranks": [
            2,
            18
          ],
          "is_new": false,
          "appearance_count": 2,
          "time_info": "[10时55分 ~ 11时43分]"
        },
        {
          "title": "前雪佛龙高管拟募集20亿美元押注委内瑞拉油业",
          "url": "https://flash.jin10.com/detail/20260105131000002800",
          "source": "金十数据",
          "ranks": [
            2,
            18
          ],
          "is_new": false,
          "appearance_count": 2,
          "time_info": "[13时19分 ~ 14时15分]"
        },
        {
          "title": "高盛寻求为日本房地产基金融资5亿美元。（彭博）",
          "url": "https://wallstreetcn.com/livenews/3030585",
          "source": "华尔街见闻-快讯",
          "ranks": [
            2,
            14
          ],
          "is_new": false,
          "appearance_count": 2,
          "time_info": "[13时19分 ~ 14时15分]"
        },
        {
          "title": "据英国《金融时报》：前雪佛龙高管为委内瑞拉石油项目寻求20亿美元资金。",
          "url": "https://flash.jin10.com/detail/20260105130231301800",
          "source": "金十数据",
          "ranks": [
            3,
            19
          ],
          "is_new": false,
          "appearance_count": 2,
          "time_info": "[13时19分 ~ 14时15分]"
        },
        {
          "title": "迪士尼(DIS.N)：《阿凡达3》全球票房突破10亿美元。",
          "url": "https://flash.jin10.com/detail/20260105011959022800",
          "source": "金十数据",
          "ranks": [
            4,
            12
          ],
          "is_new": false,
          "appearance_count": 2,
          "time_info": "[02时11分 ~ 03时07分]"
        },
        {
          "title": "消息人士：AE工业将支付逾5亿美元以持有该投资组合60%的股权，L3哈里斯公司将保留剩余的40%股权。",
          "url": "https://flash.jin10.com/detail/20260105050044880800",
          "source": "金十数据",
          "ranks": [
            5,
            15
          ],
          "is_new": false,
          "appearance_count": 2,
          "time_info": "[06时08分 ~ 07时08分]"
        },
        {
          "title": "消息人士：L3哈里斯技术公司（一家美国科技公司、国防承包商和信息技术服务提供商）即将向私人股权公司AE工业集团出售其与太空相关业务的资产，其太空资产组合总价值达8.45亿美元。",
          "url": "https://flash.jin10.com/detail/20260105045910350800",
          "source": "金十数据",
          "ranks": [
            6,
            16
          ],
          "is_new": false,
          "appearance_count": 2,
          "time_info": "[06时08分 ~ 07时08分]"
        },
        {
          "title": "野村证券：将百度(BIDU.O)目标价从140美元上调至178美元。",
          "url": "https://flash.jin10.com/detail/20260105115310152800",
          "source": "金十数据",
          "ranks": [
            14,
            27
          ],
          "is_new": false,
          "appearance_count": 2,
          "time_info": "[12时32分 ~ 13时19分]"
        },
        {
          "title": "美元兑日元USD/JPY升至157.08，创12月22日以来新高。",
          "url": "https://flash.jin10.com/detail/20260105080426341800",
          "source": "金十数据",
          "ranks": [
            6
          ],
          "is_new": false,
          "appearance_count": 1,
          "time_info": "08时37分"
        },
        {
          "title": "瑞银：预计2026年布伦特油价预测为第一季度末每桶62美元，年中每桶65美元，年底每桶67美元。",
          "url": "https://wallstreetcn.com/livenews/3030643",
          "source": "华尔街见闻-快讯",
          "ranks": [
            6
          ],
          "is_new": true,
          "appearance_count": 1,
          "time_info": "15时15分"
        },
        {
          "title": "高盛拟为日本房地产基金募集5亿美元",
          "url": "https://flash.jin10.com/detail/20260105125850731800",
          "source": "金十数据",
          "ranks": [
            8
          ],
          "is_new": false,
          "appearance_count": 1,
          "time_info": "13时19分"
        },
        {
          "title": "现货钯金涨超3%，至每盎司1,689.08美元。",
          "url": "https://wallstreetcn.com/livenews/3030397",
          "source": "华尔街见闻-快讯",
          "ranks": [
            10
          ],
          "is_new": false,
          "appearance_count": 1,
          "time_info": "08时37分"
        },
        {
          "title": "现货白银突破74美元/盎司，日内涨1.68%。",
          "url": "https://flash.jin10.com/detail/20260105075616049800",
          "source": "金十数据",
          "ranks": [
            11
          ],
          "is_new": false,
          "appearance_count": 1,
          "time_info": "08时37分"
        },
        {
          "title": "瑞银：2026年布伦特油价预测为第一季度末每桶62美元，年中每桶65美元，年底每桶67美元。",
          "url": "https://flash.jin10.com/detail/20260105145745061800",
          "source": "金十数据",
          "ranks": [
            11
          ],
          "is_new": true,
          "appearance_count": 1,
          "time_info": "15时15分"
        },
        {
          "title": "人民币兑美元中间价报7.0230，上调58点；上一交易日中间价7.0288，上一交易日官方收盘价6.9890，上日夜盘报收6.9879。",
          "url": "https://wallstreetcn.com/livenews/3030437",
          "source": "华尔街见闻-快讯",
          "ranks": [
            13
          ],
          "is_new": false,
          "appearance_count": 1,
          "time_info": "09时39分"
        },
        {
          "title": "摩根士丹利下调布伦特原油未来三个季度的价格预测。 摩根士丹利将第二季度布伦特原油价格预测下调至55美元/桶。 摩根士丹利预计全球石油过剩局面将在年中见顶。",
          "url": "https://wallstreetcn.com/livenews/3030429",
          "source": "华尔街见闻-快讯",
          "ranks": [
            19
          ],
          "is_new": false,
          "appearance_count": 1,
          "time_info": "09时39分"
        },
        {
          "title": "现货白银突破76美元/盎司，日内涨4.47%。",
          "url": "https://flash.jin10.com/detail/20260105090230081800",
          "source": "金十数据",
          "ranks": [
            25
          ],
          "is_new": false,
          "appearance_count": 1,
          "time_info": "09时39分"
        },
        {
          "title": "万科2027年11月到期美元债势创2025年11月4日以来最大涨幅，该公司3.975%债券每1美元涨2.5美分，至20.5美分。",
          "url": "https://wallstreetcn.com/livenews/3030378",
          "source": "华尔街见闻-快讯",
          "ranks": [
            25
          ],
          "is_new": false,
          "appearance_count": 1,
          "time_info": "08时37分"
        },
        {
          "title": "美元指数DXY在周一盘初小幅走强，现报98.55。",
          "url": "https://flash.jin10.com/detail/20260105070426303800",
          "source": "金十数据",
          "ranks": [
            27
          ],
          "is_new": false,
          "appearance_count": 1,
          "time_info": "08时37分"
        },
        {
          "title": "现货白银向上触及73美元/盎司，日内涨0.86%。",
          "url": "https://flash.jin10.com/detail/20260105070203870800",
          "source": "金十数据",
          "ranks": [
            28
          ],
          "is_new": false,
          "appearance_count": 1,
          "time_info": "08时37分"
        },
        {
          "title": "现货白银日内大涨4.00%，现报75.72美元/盎司。",
          "url": "https://flash.jin10.com/detail/20260105090015741800",
          "source": "金十数据",
          "ranks": [
            29
          ],
          "is_new": false,
          "appearance_count": 1,
          "time_info": "09时39分"
        }
      ]
    },
    {
      "keyword_group": "黄金",
      "match_count": 17,
      "titles": [
        {
          "title": "就在周四！黄金白银将迎新年“第一劫”：数十亿美元抛单已在路上",
          "url": "https://www.cls.cn/detail/2246895",
          "source": "财联社热门",
          "ranks": [
            4
          ],
          "is_new": false,
          "appearance_count": 13,
          "time_info": "[00时08分 ~ 07时08分]"
        },
        {
          "title": "市场对委内瑞拉变局的反应：油价“不涨反跌”，黄金重回4400，银价飙涨5%",
          "url": "https://wallstreetcn.com/articles/3762520",
          "source": "华尔街见闻",
          "ranks": [
            9,
            5,
            4
          ],
          "is_new": false,
          "appearance_count": 7,
          "time_info": "[10时55分 ~ 15时15分]"
        },
        {
          "title": "委内瑞拉现在这情况周一会对黄金和股市产生什么样的影响?",
          "url": "https://www.zhihu.com/question/1990861679899209879",
          "source": "知乎",
          "ranks": [
            13,
            14,
            15,
            19
          ],
          "is_new": false,
          "appearance_count": 9,
          "time_info": "[08时36分 ~ 13时19分]"
        },
        {
          "title": "黄金",
          "url": "https://s.weibo.com/weibo?q=%E9%BB%84%E9%87%91&t=31&band_rank=6&Refer=top",
          "source": "微博",
          "ranks": [
            6,
            22,
            21,
            24,
            23,
            26
          ],
          "is_new": false,
          "appearance_count": 7,
          "time_info": "[10时55分 ~ 15时15分]"
        },
        {
          "title": "金十图示：2026年01月05日（周一）黄金ETF持仓报告",
          "url": "https://flash.jin10.com/detail/20260105064413002800",
          "source": "金十数据",
          "ranks": [
            1,
            13,
            26
          ],
          "is_new": false,
          "appearance_count": 3,
          "time_info": "[07时08分 ~ 13时19分]"
        },
        {
          "title": "黄金再度直线猛拉",
          "url": "https://s.weibo.com/weibo?q=%23%E9%BB%84%E9%87%91%E5%86%8D%E5%BA%A6%E7%9B%B4%E7%BA%BF%E7%8C%9B%E6%8B%89%23&t=31&band_rank=10&Refer=top",
          "source": "微博",
          "ranks": [
            10,
            25
          ],
          "is_new": false,
          "appearance_count": 3,
          "time_info": "[09时38分 ~ 10时55分]"
        },
        {
          "title": "现货黄金日内一度大涨2.00%，最高触及4420美元/盎司。",
          "url": "https://flash.jin10.com/detail/20260105090908430800",
          "source": "金十数据",
          "ranks": [
            15
          ],
          "is_new": false,
          "appearance_count": 1,
          "time_info": "09时39分"
        },
        {
          "title": "现货黄金上涨近1%报4373美元/盎司，现货白银涨1.76%报73.94美元/盎司。",
          "url": "https://wallstreetcn.com/livenews/3030391",
          "source": "华尔街见闻-快讯",
          "ranks": [
            15
          ],
          "is_new": false,
          "appearance_count": 1,
          "time_info": "08时37分"
        },
        {
          "title": "现货白银涨近5%，报76.16美元/盎司。现货黄金涨1.8%报4408美元/盎司。",
          "url": "https://wallstreetcn.com/livenews/3030427",
          "source": "华尔街见闻-快讯",
          "ranks": [
            20
          ],
          "is_new": false,
          "appearance_count": 1,
          "time_info": "09时39分"
        },
        {
          "title": "上海黄金交易所黄金T+D 1月5日（周一）早盘盘初上涨1.45%报988.5元/克；<br/>上海黄金交易所白银T+D 1月5日（周一）早盘盘初上涨2.35%报18200.0元/千克。",
          "url": "https://flash.jin10.com/detail/20260105090407105800",
          "source": "金十数据",
          "ranks": [
            24
          ],
          "is_new": false,
          "appearance_count": 1,
          "time_info": "09时39分"
        },
        {
          "title": "现货黄金突破4370美元/盎司，日内涨0.87%。",
          "url": "https://flash.jin10.com/detail/20260105071507798800",
          "source": "金十数据",
          "ranks": [
            26
          ],
          "is_new": false,
          "appearance_count": 1,
          "time_info": "08时37分"
        },
        {
          "title": "现货黄金日内涨幅扩大至2%，报4419.7美元/盎司。",
          "url": "https://wallstreetcn.com/livenews/3030612",
          "source": "华尔街见闻-快讯",
          "ranks": [
            26
          ],
          "is_new": true,
          "appearance_count": 1,
          "time_info": "15时15分"
        },
        {
          "title": "黄金投资者周报上新！",
          "url": "https://flash.jin10.com/detail/20260104200000000800",
          "source": "金十数据",
          "ranks": [
            27
          ],
          "is_new": false,
          "appearance_count": 1,
          "time_info": "00时09分"
        },
        {
          "title": "脑机接口产业迎来“黄金发展期”",
          "url": "https://www.toutiao.com/trending/7591644621160185875/",
          "source": "今日头条",
          "ranks": [
            28
          ],
          "is_new": false,
          "appearance_count": 1,
          "time_info": "12时32分"
        },
        {
          "title": "现货黄金重回4400美元关口之上，日内涨幅扩大至1.6%。",
          "url": "https://flash.jin10.com/detail/20260105090053489800",
          "source": "金十数据",
          "ranks": [
            28
          ],
          "is_new": false,
          "appearance_count": 1,
          "time_info": "09时39分"
        },
        {
          "title": "深交所公告，港股通标的证券名单发生调整并自2026年1月5日起生效，调入纳芯微，调出万国黄金集团－旧。",
          "url": "https://wallstreetcn.com/livenews/3030418",
          "source": "华尔街见闻-快讯",
          "ranks": [
            28
          ],
          "is_new": false,
          "appearance_count": 1,
          "time_info": "09时39分"
        },
        {
          "title": "现货黄金周一跳空高开，报4352.08美元/盎司。",
          "url": "https://flash.jin10.com/detail/20260105070107373800",
          "source": "金十数据",
          "ranks": [
            30
          ],
          "is_new": false,
          "appearance_count": 1,
          "time_info": "08时37分"
        }
      ]
    },
    {
      "keyword_group": "概念",
      "match_count": 9,
      "titles": [
        {
          "title": "产品深度服务于航天员在轨工作与生活保障 商业航天概念股单日涨超14% 本周机构密集调研相关上市公司",
          "url": "https://www.cls.cn/detail/2247276",
          "source": "财联社热门",
          "ranks": [
            7,
            6,
            5,
            4,
            2
          ],
          "is_new": false,
          "appearance_count": 24,
          "time_info": "[00时08分 ~ 15时15分]"
        },
        {
          "title": "为什么有些人更倾向于直接攻击「斩杀线」概念的传播者，而不是去证明「斩杀线」不存在？",
          "url": "https://www.zhihu.com/question/1989380731303122932",
          "source": "知乎",
          "ranks": [
            19,
            15,
            13,
            9,
            8
          ],
          "is_new": false,
          "appearance_count": 15,
          "time_info": "[00时08分 ~ 09时39分]"
        },
        {
          "title": "商业航天概念延续涨势，雷科防务4连板，金风科技一字涨停，联创光电、久之洋、航天环宇、中国卫通等涨超6%，消息上，蓝箭航天科创板IPO获受理，公司拟融资金额75亿元。",
          "url": "https://wallstreetcn.com/livenews/3030454",
          "source": "华尔街见闻-快讯",
          "ranks": [
            3
          ],
          "is_new": false,
          "appearance_count": 1,
          "time_info": "09时39分"
        },
        {
          "title": "A股开门红！沪指涨1.38%重回4000点，中证A500指数创阶段新高，脑机接口概念掀涨停潮",
          "url": "https://wallstreetcn.com/livenews/3030644",
          "source": "华尔街见闻-快讯",
          "ranks": [
            5
          ],
          "is_new": true,
          "appearance_count": 1,
          "time_info": "15时15分"
        },
        {
          "title": "A股PCB概念股震荡拉升，胜宏科技涨近10%，深南电路涨近5%，股价续创历史新高，方邦股份、一博科技、方正科技、沪电股份、生益电子跟涨。",
          "url": "https://wallstreetcn.com/livenews/3030608",
          "source": "华尔街见闻-快讯",
          "ranks": [
            1,
            27
          ],
          "is_new": false,
          "appearance_count": 2,
          "time_info": "[14时15分 ~ 15时15分]"
        },
        {
          "title": "1月5日午间收评：沪指涨超1%重返4000点，脑机接口概念掀涨停潮",
          "url": "https://wallstreetcn.com/livenews/3030529",
          "source": "华尔街见闻-快讯",
          "ranks": [
            4,
            22
          ],
          "is_new": false,
          "appearance_count": 2,
          "time_info": "[11时43分 ~ 12时32分]"
        },
        {
          "title": "A股脑机接口概念开盘大涨，三博脑科、美好医疗、岩山科技、创新医疗、南京熊猫等多股竞价涨停，翔宇医疗、爱朋医疗等涨超10%。",
          "url": "https://wallstreetcn.com/livenews/3030448",
          "source": "华尔街见闻-快讯",
          "ranks": [
            7,
            27
          ],
          "is_new": false,
          "appearance_count": 2,
          "time_info": "[09时39分 ~ 10时55分]"
        },
        {
          "title": "【午报】沪指涨超1%重返4000点，脑机接口概念20余股涨停，商业航天反复活跃",
          "url": "https://www.cls.cn/detail/2247674",
          "source": "财联社热门",
          "ranks": [
            13
          ],
          "is_new": true,
          "appearance_count": 1,
          "time_info": "15时15分"
        },
        {
          "title": "A股商业航天概念延续涨势，雷科防务4连板，金风科技一字涨停，联创光电、久之洋、航天环宇、中国卫通等涨超6%，消息上，蓝箭航天科创板IPO获受理，公司拟融资金额75亿元。",
          "url": "https://wallstreetcn.com/livenews/3030454",
          "source": "华尔街见闻-快讯",
          "ranks": [
            23
          ],
          "is_new": false,
          "appearance_count": 1,
          "time_info": "10时55分"
        }
      ]
    },
    {
      "keyword_group": "金价",
      "match_count": 2,
      "titles": [
        {
          "title": "金十图示：2026年01月05日（周一）上海金午盘价为992.86元/克，较国际金价(991.31元/克)，高1.55元/克",
          "url": "https://flash.jin10.com/detail/20260105150258794800",
          "source": "金十数据",
          "ranks": [
            3
          ],
          "is_new": true,
          "appearance_count": 1,
          "time_info": "15时15分"
        },
        {
          "title": "金十图示：2026年01月05日（周一）上海金早盘价为988.04元/克，较国际金价(985.96元/克)，高2.08元/克",
          "url": "https://flash.jin10.com/detail/20260105102225187800",
          "source": "金十数据",
          "ranks": [
            10
          ],
          "is_new": false,
          "appearance_count": 1,
          "time_info": "10时55分"
        }
      ]
    },
    {
      "keyword_group": "美股",
      "match_count": 1,
      "titles": [
        {
          "title": "美股三大股指期货周一小幅高开。",
          "url": "https://flash.jin10.com/detail/20260105070122345800",
          "source": "金十数据",
          "ranks": [
            29
          ],
          "is_new": false,
          "appearance_count": 1,
          "time_info": "08时37分"
        }
      ]
    },
    {
      "keyword_group": "美债",
      "match_count": 1,
      "titles": [
        {
          "title": "凯投宏观：委内瑞拉供给变动不会对美债产生显著影响",
          "url": "https://flash.jin10.com/detail/20260105145449593800",
          "source": "金十数据",
          "ranks": [
            14
          ],
          "is_new": true,
          "appearance_count": 1,
          "time_info": "15时15分"
        }
      ]
    }
  ],
  "report_image_url": "https://joyce677.github.io/TrendRadar/img/news.jpg"
}